neuropercept/__init__.py
neuropercept/perceptron.py
neuropercept_PratikBorkar04-0.0.1.dist-info/LICENSE
neuropercept_PratikBorkar04-0.0.1.dist-info/METADATA
neuropercept_PratikBorkar04-0.0.1.dist-info/WHEEL
neuropercept_PratikBorkar04-0.0.1.dist-info/top_level.txt
neuropercept_PratikBorkar04-0.0.1.dist-info/RECORD
