Metadata-Version: 2.1
Name: neuropercept-PratikBorkar04
Version: 0.0.1
Summary: Implementation of Perceptron
Home-page: https://github.com/PratikBorkar04/neuropercept
Author: PratikBorkar04
Author-email: pratikab01@gmail.com
Project-URL: Bug Tracker, https://github.com/PratikBorkar04/neuropercept/issues
Classifier: Programming Language :: Python :: 3
Classifier: License :: OSI Approved :: MIT License
Classifier: Operating System :: OS Independent
Requires-Python: >=3.7
License-File: LICENSE
Requires-Dist: numpy
Requires-Dist: tqdm
